CHANGELOG.md
LICENSE
social_arsenal/__init__.py
social_arsenal/config.py
social_arsenal/filename_extractor.py
social_arsenal/files/image_file.py
social_arsenal/files/pdf_file.py
social_arsenal/files/sortable_file.py
social_arsenal/name_images.py
social_arsenal/sorter.py
social_arsenal/sorting_rules/crypto.csv
social_arsenal/util/argument_parser.py
social_arsenal/util/dict_helper.py
social_arsenal/util/filesystem_helper.py
social_arsenal/util/logging.py
social_arsenal/util/rich_helper.py
social_arsenal/util/string_helper.py
social_arsenal-0.2.3.dist-info/LICENSE
social_arsenal-0.2.3.dist-info/WHEEL
social_arsenal-0.2.3.dist-info/entry_points.txt
social_arsenal-0.2.3.dist-info/METADATA
social_arsenal-0.2.3.dist-info/RECORD
